Workbook

Sheet Listas de itens
D3: Janeiro | E3: Fevereiro | F3: Março | G3: Abril | H3: Maio | I3: Junho | J3: Julho | K3: Agosto | L3: Setembro | M3: Outubro | N3: Novembro | O3: Dezembro
D5: Valor | E5: Valor | F5: Valor | G5: Valor | H5: Valor | I5: Valor | J5: Valor | K5: Valor | L5: Valor | M5: Valor | N5: Valor | O5: Valor
A6: Receitas | C6: Salário | D6: =Receitas!E4 | E6: =Receitas!H4 | F6: =Receitas!K4 | G6: =Receitas!N4 | H6: =Receitas!Q4 | I6: =Receitas!T4 | J6: =Receitas!W4 | K6: =Receitas!Z4 | L6: =Receitas!AC4 | M6: =Receitas!AF4 | N6: =Receitas!AI4 | O6: =Receitas!AL4
C7: 13° | D7: =Receitas!E6 | E7: =Receitas!H6 | F7: =Receitas!K6 | G7: =Receitas!N6 | H7: =Receitas!Q6 | I7: =Receitas!T6 | J7: =Receitas!W6 | K7: =Receitas!Z6 | L7: =Receitas!AC6 | M7: =Receitas!AF6 | N7: =Receitas!AI6 | O7: =Receitas!AL6
C9: Total | D9: =SUM(D6:D7) | E9: =SUM(E6:E7) | F9: =SUM(F6:F7) | G9: =SUM(G6:G7) | H9: =SUM(H6:H7) | I9: =SUM(I6:I7) | J9: =SUM(J6:J7) | K9: =SUM(K6:K7) | ... O9: =SUM(O6:O7)
C12: Investimentos
C13: Total | D13: =D12 | E13: =E12 | F13: =F12 | G13: =G12 | H13: =H12 | I13: =I12 | J13: =J12 | K13: =K12 | ... O13: =O12
C14: % sobre receita | D14: =IF(D9>0,D13/D9,0) | E14: =IF(E9>0,E13/E9,0) | F14: =IF(F9>0,F13/F9,0) | G14: =IF(G9>0,G13/G9,0) | H14: =IF(H9>0,H13/H9,0) | I14: =IF(I9>0,I13/I9,0) | J14: =IF(J9>0,J13/J9,0) | K14: =IF(K9>0,K13/K9,0) | ... O14: =IF(O9>0,O13/O9,0)
A18: Fixas | B18: Habitação | C18: Diarista | D18: =Fixas!E6 | E18: =Fixas!H6 | F18: =Fixas!K6 | G18: =Fixas!N6 | H18: =Fixas!Q6 | I18: =Fixas!T6 | J18: =Fixas!W6 | K18: =Fixas!Z6 | L18: =Fixas!AC6 | M18: =Fixas!AF6 | N18: =Fixas!AI6 | O18: =Fixas!AL6
C19: Aluguel | D19: =Fixas!E9 | E19: =Fixas!H9 | F19: =Fixas!K9 | G19: =Fixas!N9 | H19: =Fixas!Q9 | I19: =Fixas!T9 | J19: =Fixas!W9 | K19: =Fixas!Z9 | L19: =Fixas!AC9 | M19: =Fixas!AF9 | N19: =Fixas!AI9 | O19: =Fixas!AL9
B20: Total Habitação | D20: =SUM(D18:D19) | E20: =SUM(E18:E19) | F20: =SUM(F18:F19) | G20: =SUM(G18:G19) | H20: =SUM(H18:H19) | I20: =SUM(I18:I19) | J20: =SUM(J18:J19) | K20: =SUM(K18:K19) | ... O20: =SUM(O18:O19)
B21: % sobre despesas | D21: =IF(D28>0,D20/D28,0) | E21: =IF(E28>0,E20/E28,0) | F21: =IF(F28>0,F20/F28,0) | G21: =IF(G28>0,G20/G28,0) | H21: =IF(H28>0,H20/H28,0) | I21: =IF(I28>0,I20/I28,0) | J21: =IF(J28>0,J20/J28,0) | K21: =IF(K28>0,K20/K28,0) | ... O21: =IF(O28>0,O20/O28,0)
B22: % sobre receita | D22: =IF(D9>0,D20/D9,0) | E22: =IF(E9>0,E20/E9,0) | F22: =IF(F9>0,F20/F9,0) | G22: =IF(G9>0,G20/G9,0) | H22: =IF(H9>0,H20/H9,0) | I22: =IF(I9>0,I20/I9,0) | J22: =IF(J9>0,J20/J9,0) | K22: =IF(K9>0,K20/K9,0) | ... O22: =IF(O9>0,O20/O9,0)
B23: Lazer | C23: Netflix | D23: =Fixas!E14 | E23: =Fixas!H14 | F23: =Fixas!K14 | G23: =Fixas!N14 | H23: =Fixas!Q14 | I23: =Fixas!T14 | J23: =Fixas!W14 | K23: =Fixas!Z14 | L23: =Fixas!AC14 | M23: =Fixas!AF14 | N23: =Fixas!AI14 | O23: =Fixas!AL14
C24: Spotify | D24: =Fixas!E16 | E24: =Fixas!H16 | F24: =Fixas!K16 | G24: =Fixas!N16 | H24: =Fixas!Q16 | I24: =Fixas!T16 | J24: =Fixas!W16 | K24: =Fixas!Z16 | L24: =Fixas!AC16 | M24: =Fixas!AF16 | N24: =Fixas!AI16 | O24: =Fixas!AL16
B25: Total Lazer | D25: =SUM(D23:D24) | E25: =SUM(E23:E24) | F25: =SUM(F23:F24) | G25: =SUM(G23:G24) | H25: =SUM(H23:H24) | I25: =SUM(I23:I24) | J25: =SUM(J23:J24) | K25: =SUM(K23:K24) | ... O25: =SUM(O23:O24)
B26: % sobre despesas | D26: =IF(D28>0,D25/D28,0) | E26: =IF(E28>0,E25/E28,0) | F26: =IF(F28>0,F25/F28,0) | G26: =IF(G28>0,G25/G28,0) | H26: =IF(H28>0,H25/H28,0) | I26: =IF(I28>0,I25/I28,0) | J26: =IF(J28>0,J25/J28,0) | K26: =IF(K28>0,K25/K28,0) | ... O26: =IF(O28>0,O25/O28,0)
B27: % sobre receita | D27: =IF(D9>0,D25/D9,0) | E27: =IF(E9>0,E25/E9,0) | F27: =IF(F9>0,F25/F9,0) | G27: =IF(G9>0,G25/G9,0) | H27: =IF(H9>0,H25/H9,0) | I27: =IF(I9>0,I25/I9,0) | J27: =IF(J9>0,J25/J9,0) | K27: =IF(K9>0,K25/K9,0) | ... O27: =IF(O9>0,O25/O9,0)
B28: Total despesas fixas | D28: =SUM(D20,D25) | E28: =SUM(E20,E25) | F28: =SUM(F20,F25) | G28: =SUM(G20,G25) | H28: =SUM(H20,H25) | I28: =SUM(I20,I25) | J28: =SUM(J20,J25) | K28: =SUM(K20,K25) | ... O28: =SUM(O20,O25)
B30: % sobre receita | D30: =IF(D9>0,D28/D9,0) | E30: =IF(E9>0,E28/E9,0) | F30: =IF(F9>0,F28/F9,0) | G30: =IF(G9>0,G28/G9,0) | H30: =IF(H9>0,H28/H9,0) | I30: =IF(I9>0,I28/I9,0) | J30: =IF(J9>0,J28/J9,0) | K30: =IF(K9>0,K28/K9,0) | ... O30: =IF(O9>0,O28/O9,0)
A32: Variáveis | B32: Alimentação / Limpeza | C32: Supermercado | D32: ='Variáveis'!E4 | E32: ='Variáveis'!H4 | F32: ='Variáveis'!K4 | G32: ='Variáveis'!N4 | H32: ='Variáveis'!Q4 | I32: ='Variáveis'!T4 | J32: ='Variáveis'!W4 | K32: ='Variáveis'!Z4 | L32: ='Variáveis'!AC4 | M32: ='Variáveis'!AF4 | N32: ='Variáveis'!AI4 | O32: ='Variáveis'!AL4
C33: Padaria | D33: ='Variáveis'!E6 | E33: ='Variáveis'!H6 | F33: ='Variáveis'!K6 | G33: ='Variáveis'!N6 | H33: ='Variáveis'!Q6 | I33: ='Variáveis'!T6 | J33: ='Variáveis'!W6 | K33: ='Variáveis'!Z6 | L33: ='Variáveis'!AC6 | M33: ='Variáveis'!AF6 | N33: ='Variáveis'!AI6 | O33: ='Variáveis'!AL6
B34: Total Alimentação / Limpeza | D34: =SUM(D32:D33) | E34: =SUM(E32:E33) | F34: =SUM(F32:F33) | G34: =SUM(G32:G33) | H34: =SUM(H32:H33) | I34: =SUM(I32:I33) | J34: =SUM(J32:J33) | K34: =SUM(K32:K33) | ... O34: =SUM(O32:O33)
B35: % sobre despesas | D35: =IF(D46>0,D34/D46,0) | E35: =IF(E46>0,E34/E46,0) | F35: =IF(F46>0,F34/F46,0) | G35: =IF(G46>0,G34/G46,0) | H35: =IF(H46>0,H34/H46,0) | I35: =IF(I46>0,I34/I46,0) | J35: =IF(J46>0,J34/J46,0) | K35: =IF(K46>0,K34/K46,0) | ... O35: =IF(O46>0,O34/O46,0)
B36: % sobre receita | D36: =IF(D9>0,D34/D9,0) | E36: =IF(E9>0,E34/E9,0) | F36: =IF(F9>0,F34/F9,0) | G36: =IF(G9>0,G34/G9,0) | H36: =IF(H9>0,H34/H9,0) | I36: =IF(I9>0,I34/I9,0) | J36: =IF(J9>0,J34/J9,0) | K36: =IF(K9>0,K34/K9,0) | ... O36: =IF(O9>0,O34/O9,0)
B37: Pets | C37: Orion - Consultas | D37: ='Variáveis'!E11 | E37: ='Variáveis'!H11 | F37: ='Variáveis'!K11 | G37: ='Variáveis'!N11 | H37: ='Variáveis'!Q11 | I37: ='Variáveis'!T11 | J37: ='Variáveis'!W11 | K37: ='Variáveis'!Z11 | L37: ='Variáveis'!AC11 | M37: ='Variáveis'!AF11 | N37: ='Variáveis'!AI11 | O37: ='Variáveis'!AL11
C38: Orion - Ração | D38: ='Variáveis'!E13 | E38: ='Variáveis'!H13 | F38: ='Variáveis'!K13 | G38: ='Variáveis'!N13 | H38: ='Variáveis'!Q13 | I38: ='Variáveis'!T13 | J38: ='Variáveis'!W13 | K38: ='Variáveis'!Z13 | L38: ='Variáveis'!AC13 | M38: ='Variáveis'!AF13 | N38: ='Variáveis'!AI13 | O38: ='Variáveis'!AL13
B39: Total Pets | D39: =SUM(D37:D38) | E39: =SUM(E37:E38) | F39: =SUM(F37:F38) | G39: =SUM(G37:G38) | H39: =SUM(H37:H38) | I39: =SUM(I37:I38) | J39: =SUM(J37:J38) | K39: =SUM(K37:K38) | ... O39: =SUM(O37:O38)
B40: % sobre despesas | D40: =IF(D46>0,D39/D46,0) | E40: =IF(E46>0,E39/E46,0) | F40: =IF(F46>0,F39/F46,0) | G40: =IF(G46>0,G39/G46,0) | H40: =IF(H46>0,H39/H46,0) | I40: =IF(I46>0,I39/I46,0) | J40: =IF(J46>0,J39/J46,0) | K40: =IF(K46>0,K39/K46,0) | ... O40: =IF(O46>0,O39/O46,0)
B41: % sobre receita | D41: =IF(D9>0,D39/D9,0) | E41: =IF(E9>0,E39/E9,0) | F41: =IF(F9>0,F39/F9,0) | G41: =IF(G9>0,G39/G9,0) | H41: =IF(H9>0,H39/H9,0) | I41: =IF(I9>0,I39/I9,0) | J41: =IF(J9>0,J39/J9,0) | K41: =IF(K9>0,K39/K9,0) | ... O41: =IF(O9>0,O39/O9,0)
B42: Transporte | C42: Metrô | D42: ='Variáveis'!E18 | E42: ='Variáveis'!H18 | F42: ='Variáveis'!K18 | G42: ='Variáveis'!N18 | H42: ='Variáveis'!Q18 | I42: ='Variáveis'!T18 | J42: ='Variáveis'!W18 | K42: ='Variáveis'!Z18 | L42: ='Variáveis'!AC18 | M42: ='Variáveis'!AF18 | N42: ='Variáveis'!AI18 | O42: ='Variáveis'!AL18
B43: Total Transporte | D43: =SUM(D42) | E43: =SUM(E42) | F43: =SUM(F42) | G43: =SUM(G42) | H43: =SUM(H42) | I43: =SUM(I42) | J43: =SUM(J42) | K43: =SUM(K42) | ... O43: =SUM(O42)
B44: % sobre despesas | D44: =IF(D46>0,D43/D46,0) | E44: =IF(E46>0,E43/E46,0) | F44: =IF(F46>0,F43/F46,0) | G44: =IF(G46>0,G43/G46,0) | H44: =IF(H46>0,H43/H46,0) | I44: =IF(I46>0,I43/I46,0) | J44: =IF(J46>0,J43/J46,0) | K44: =IF(K46>0,K43/K46,0) | ... O44: =IF(O46>0,O43/O46,0)
B45: % sobre receita | D45: =IF(D9>0,D43/D9,0) | E45: =IF(E9>0,E43/E9,0) | F45: =IF(F9>0,F43/F9,0) | G45: =IF(G9>0,G43/G9,0) | H45: =IF(H9>0,H43/H9,0) | I45: =IF(I9>0,I43/I9,0) | J45: =IF(J9>0,J43/J9,0) | K45: =IF(K9>0,K43/K9,0) | ... O45: =IF(O9>0,O43/O9,0)
B46: Total despesas variáveis | D46: =SUM(D34,D39,D43) | E46: =SUM(E34,E39,E43) | F46: =SUM(F34,F39,F43) | G46: =SUM(G34,G39,G43) | H46: =SUM(H34,H39,H43) | I46: =SUM(I34,I39,I43) | J46: =SUM(J34,J39,J43) | K46: =SUM(K34,K39,K43) | ... O46: =SUM(O34,O39,O43)
B48: % sobre receita | D48: =IF(D9>0,D46/D9,0) | E48: =IF(E9>0,E46/E9,0) | F48: =IF(F9>0,F46/F9,0) | G48: =IF(G9>0,G46/G9,0) | H48: =IF(H9>0,H46/H9,0) | I48: =IF(I9>0,I46/I9,0) | J48: =IF(J9>0,J46/J9,0) | K48: =IF(K9>0,K46/K9,0) | ... O48: =IF(O9>0,O46/O9,0)
A50: Extras | B50: Saúde | C50: Médico | D50: =Extras!E4 | E50: =Extras!H4 | F50: =Extras!K4 | G50: =Extras!N4 | H50: =Extras!Q4 | I50: =Extras!T4 | J50: =Extras!W4 | K50: =Extras!Z4 | L50: =Extras!AC4 | M50: =Extras!AF4 | N50: =Extras!AI4 | O50: =Extras!AL4
C51: Dentista | D51: =Extras!E6 | E51: =Extras!H6 | F51: =Extras!K6 | G51: =Extras!N6 | H51: =Extras!Q6 | I51: =Extras!T6 | J51: =Extras!W6 | K51: =Extras!Z6 | L51: =Extras!AC6 | M51: =Extras!AF6 | N51: =Extras!AI6 | O51: =Extras!AL6
B52: Total Saúde | D52: =SUM(D50:D51) | E52: =SUM(E50:E51) | F52: =SUM(F50:F51) | G52: =SUM(G50:G51) | H52: =SUM(H50:H51) | I52: =SUM(I50:I51) | J52: =SUM(J50:J51) | K52: =SUM(K50:K51) | ... O52: =SUM(O50:O51)
B53: % sobre despesas | D53: =IF(D60>0,D52/D60,0) | E53: =IF(E60>0,E52/E60,0) | F53: =IF(F60>0,F52/F60,0) | G53: =IF(G60>0,G52/G60,0) | H53: =IF(H60>0,H52/H60,0) | I53: =IF(I60>0,I52/I60,0) | J53: =IF(J60>0,J52/J60,0) | K53: =IF(K60>0,K52/K60,0) | ... O53: =IF(O60>0,O52/O60,0)
B54: % sobre receita | D54: =IF(D9>0,D52/D9,0) | E54: =IF(E9>0,E52/E9,0) | F54: =IF(F9>0,F52/F9,0) | G54: =IF(G9>0,G52/G9,0) | H54: =IF(H9>0,H52/H9,0) | I54: =IF(I9>0,I52/I9,0) | J54: =IF(J9>0,J52/J9,0) | K54: =IF(K9>0,K52/K9,0) | ... O54: =IF(O9>0,O52/O9,0)
B55: Manutenção / prevenção | C55: Carro | D55: =Extras!E11 | E55: =Extras!H11 | F55: =Extras!K11 | G55: =Extras!N11 | H55: =Extras!Q11 | I55: =Extras!T11 | J55: =Extras!W11 | K55: =Extras!Z11 | L55: =Extras!AC11 | M55: =Extras!AF11 | N55: =Extras!AI11 | O55: =Extras!AL11
C56: Casa | D56: =Extras!E13 | E56: =Extras!H13 | F56: =Extras!K13 | G56: =Extras!N13 | H56: =Extras!Q13 | I56: =Extras!T13 | J56: =Extras!W13 | K56: =Extras!Z13 | L56: =Extras!AC13 | M56: =Extras!AF13 | N56: =Extras!AI13 | O56: =Extras!AL13
B57: Total Manutenção / prevenção | D57: =SUM(D55:D56) | E57: =SUM(E55:E56) | F57: =SUM(F55:F56) | G57: =SUM(G55:G56) | H57: =SUM(H55:H56) | I57: =SUM(I55:I56) | J57: =SUM(J55:J56) | K57: =SUM(K55:K56) | ... O57: =SUM(O55:O56)
B58: % sobre despesas | D58: =IF(D60>0,D57/D60,0) | E58: =IF(E60>0,E57/E60,0) | F58: =IF(F60>0,F57/F60,0) | G58: =IF(G60>0,G57/G60,0) | H58: =IF(H60>0,H57/H60,0) | I58: =IF(I60>0,I57/I60,0) | J58: =IF(J60>0,J57/J60,0) | K58: =IF(K60>0,K57/K60,0) | ... O58: =IF(O60>0,O57/O60,0)
B59: % sobre receita | D59: =IF(D9>0,D57/D9,0) | E59: =IF(E9>0,E57/E9,0) | F59: =IF(F9>0,F57/F9,0) | G59: =IF(G9>0,G57/G9,0) | H59: =IF(H9>0,H57/H9,0) | I59: =IF(I9>0,I57/I9,0) | J59: =IF(J9>0,J57/J9,0) | K59: =IF(K9>0,K57/K9,0) | ... O59: =IF(O9>0,O57/O9,0)
B60: Total despesas extras | D60: =SUM(D52,D57) | E60: =SUM(E52,E57) | F60: =SUM(F52,F57) | G60: =SUM(G52,G57) | H60: =SUM(H52,H57) | I60: =SUM(I52,I57) | J60: =SUM(J52,J57) | K60: =SUM(K52,K57) | ... O60: =SUM(O52,O57)
B62: % sobre receita | D62: =IF(D9>0,D60/D9,0) | E62: =IF(E9>0,E60/E9,0) | F62: =IF(F9>0,F60/F9,0) | G62: =IF(G9>0,G60/G9,0) | H62: =IF(H9>0,H60/H9,0) | I62: =IF(I9>0,I60/I9,0) | J62: =IF(J9>0,J60/J9,0) | K62: =IF(K9>0,K60/K9,0) | ... O62: =IF(O9>0,O60/O9,0)
A64: Adicionais | B64: Lazer | C64: Viagens | D64: =Adicionais!E4 | E64: =Adicionais!H4 | F64: =Adicionais!K4 | G64: =Adicionais!N4 | H64: =Adicionais!Q4 | I64: =Adicionais!T4 | J64: =Adicionais!W4 | K64: =Adicionais!Z4 | L64: =Adicionais!AC4 | M64: =Adicionais!AF4 | N64: =Adicionais!AI4 | O64: =Adicionais!AL4
C65: Jogos | D65: =Adicionais!E6 | E65: =Adicionais!H6 | F65: =Adicionais!K6 | G65: =Adicionais!N6 | H65: =Adicionais!Q6 | I65: =Adicionais!T6 | J65: =Adicionais!W6 | K65: =Adicionais!Z6 | L65: =Adicionais!AC6 | M65: =Adicionais!AF6 | N65: =Adicionais!AI6 | O65: =Adicionais!AL6
B66: Total Lazer | D66: =SUM(D64:D65) | E66: =SUM(E64:E65) | F66: =SUM(F64:F65) | G66: =SUM(G64:G65) | H66: =SUM(H64:H65) | I66: =SUM(I64:I65) | J66: =SUM(J64:J65) | K66: =SUM(K64:K65) | ... O66: =SUM(O64:O65)
B67: % sobre despesas | D67: =IF(D74>0,D66/D74,0) | E67: =IF(E74>0,E66/E74,0) | F67: =IF(F74>0,F66/F74,0) | G67: =IF(G74>0,G66/G74,0) | H67: =IF(H74>0,H66/H74,0) | I67: =IF(I74>0,I66/I74,0) | J67: =IF(J74>0,J66/J74,0) | K67: =IF(K74>0,K66/K74,0) | ... O67: =IF(O74>0,O66/O74,0)
B68: % sobre receita | D68: =IF(D9>0,D66/D9,0) | E68: =IF(E9>0,E66/E9,0) | F68: =IF(F9>0,F66/F9,0) | G68: =IF(G9>0,G66/G9,0) | H68: =IF(H9>0,H66/H9,0) | I68: =IF(I9>0,I66/I9,0) | J68: =IF(J9>0,J66/J9,0) | K68: =IF(K9>0,K66/K9,0) | ... O68: =IF(O9>0,O66/O9,0)
B69: Outros | C69: Presentes | D69: =Adicionais!E11 | E69: =Adicionais!H11 | F69: =Adicionais!K11 | G69: =Adicionais!N11 | H69: =Adicionais!Q11 | I69: =Adicionais!T11 | J69: =Adicionais!W11 | K69: =Adicionais!Z11 | L69: =Adicionais!AC11 | M69: =Adicionais!AF11 | N69: =Adicionais!AI11 | O69: =Adicionais!AL11
C70: Papelaria | D70: =Adicionais!E13 | E70: =Adicionais!H13 | F70: =Adicionais!K13 | G70: =Adicionais!N13 | H70: =Adicionais!Q13 | I70: =Adicionais!T13 | J70: =Adicionais!W13 | K70: =Adicionais!Z13 | L70: =Adicionais!AC13 | M70: =Adicionais!AF13 | N70: =Adicionais!AI13 | O70: =Adicionais!AL13
B71: Total Outros | D71: =SUM(D69:D70) | E71: =SUM(E69:E70) | F71: =SUM(F69:F70) | G71: =SUM(G69:G70) | H71: =SUM(H69:H70) | I71: =SUM(I69:I70) | J71: =SUM(J69:J70) | K71: =SUM(K69:K70) | ... O71: =SUM(O69:O70)
B72: % sobre despesas | D72: =IF(D74>0,D71/D74,0) | E72: =IF(E74>0,E71/E74,0) | F72: =IF(F74>0,F71/F74,0) | G72: =IF(G74>0,G71/G74,0) | H72: =IF(H74>0,H71/H74,0) | I72: =IF(I74>0,I71/I74,0) | J72: =IF(J74>0,J71/J74,0) | K72: =IF(K74>0,K71/K74,0) | ... O72: =IF(O74>0,O71/O74,0)
B73: % sobre receita | D73: =IF(D9>0,D71/D9,0) | E73: =IF(E9>0,E71/E9,0) | F73: =IF(F9>0,F71/F9,0) | G73: =IF(G9>0,G71/G9,0) | H73: =IF(H9>0,H71/H9,0) | I73: =IF(I9>0,I71/I9,0) | J73: =IF(J9>0,J71/J9,0) | K73: =IF(K9>0,K71/K9,0) | ... O73: =IF(O9>0,O71/O9,0)
B74: Total despesas adicionais | D74: =SUM(D66,D71) | E74: =SUM(E66,E71) | F74: =SUM(F66,F71) | G74: =SUM(G66,G71) | H74: =SUM(H66,H71) | I74: =SUM(I66,I71) | J74: =SUM(J66,J71) | K74: =SUM(K66,K71) | ... O74: =SUM(O66,O71)
B76: % sobre receita | D76: =IF(D9>0,D74/D9,0) | E76: =IF(E9>0,E74/E9,0) | F76: =IF(F9>0,F74/F9,0) | G76: =IF(G9>0,G74/G9,0) | H76: =IF(H9>0,H74/H9,0) | I76: =IF(I9>0,I74/I9,0) | J76: =IF(J9>0,J74/J9,0) | K76: =IF(K9>0,K74/K9,0) | ... O76: =IF(O9>0,O74/O9,0)
A79: Receita | D79: =D9 | E79: =E9 | F79: =F9 | G79: =G9 | H79: =H9 | I79: =I9 | J79: =J9 | K79: =K9 | ... O79: =O9
A80: Investimentos | D80: =D13 | E80: =E13 | F80: =F13 | G80: =G13 | H80: =H13 | I80: =I13 | J80: =J13 | K80: =K13 | ... O80: =O13
A81: Total renda | D81: =SUM(D79:D80) | E81: =SUM(E79:E80) | F81: =SUM(F79:F80) | G81: =SUM(G79:G80) | H81: =SUM(H79:H80) | I81: =SUM(I79:I80) | J81: =SUM(J79:J80) | K81: =SUM(K79:K80) | ... O81: =SUM(O79:O80)
A82: Despesas fixas | D82: =D28 | E82: =E28 | F82: =F28 | G82: =G28 | H82: =H28 | I82: =I28 | J82: =J28 | K82: =K28 | ... O82: =O28
A83: Despesas variáveis | D83: =D46 | E83: =E46 | F83: =F46 | G83: =G46 | H83: =H46 | I83: =I46 | J83: =J46 | K83: =K46 | ... O83: =O46
A84: Despesas extras | D84: =D60 | E84: =E60 | F84: =F60 | G84: =G60 | H84: =H60 | I84: =I60 | J84: =J60 | K84: =K60 | ... O84: =O60
A85: Despesas adicionais | D85: =D74 | E85: =E74 | F85: =F74 | G85: =G74 | H85: =H74 | I85: =I74 | J85: =J74 | K85: =K74 | ... O85: =O74
A86: Total despesas | D86: =SUM(D82,D83,D84,D85) | E86: =SUM(E82,E83,E84,E85) | F86: =SUM(F82,F83,F84,F85) | G86: =SUM(G82,G83,G84,G85) | H86: =SUM(H82,H83,H84,H85) | I86: =SUM(I82,I83,I84,I85) | J86: =SUM(J82,J83,J84,J85) | K86: =SUM(K82,K83,K84,K85) | ... O86: =SUM(O82,O83,O84,O85)
A87: Porcentagem da despesa
A88: Fixas | D88: =IF(D86>0,D82/D86,0) | E88: =IF(E86>0,E82/E86,0) | F88: =IF(F86>0,F82/F86,0) | G88: =IF(G86>0,G82/G86,0) | H88: =IF(H86>0,H82/H86,0) | I88: =IF(I86>0,I82/I86,0) | J88: =IF(J86>0,J82/J86,0) | K88: =IF(K86>0,K82/K86,0) | ... O88: =IF(O86>0,O82/O86,0)
A89: Variáveis | D89: =IF(D86>0,D83/D86,0) | E89: =IF(E86>0,E83/E86,0) | F89: =IF(F86>0,F83/F86,0) | G89: =IF(G86>0,G83/G86,0) | H89: =IF(H86>0,H83/H86,0) | I89: =IF(I86>0,I83/I86,0) | J89: =IF(J86>0,J83/J86,0) | K89: =IF(K86>0,K83/K86,0) | ... O89: =IF(O86>0,O83/O86,0)
A90: Extras | D90: =IF(D86>0,D84/D86,0) | E90: =IF(E86>0,E84/E86,0) | F90: =IF(F86>0,F84/F86,0) | G90: =IF(G86>0,G84/G86,0) | H90: =IF(H86>0,H84/H86,0) | I90: =IF(I86>0,I84/I86,0) | J90: =IF(J86>0,J84/J86,0) | K90: =IF(K86>0,K84/K86,0) | ... O90: =IF(O86>0,O84/O86,0)
A91: Adicionais | D91: =IF(D86>0,D85/D86,0) | E91: =IF(E86>0,E85/E86,0) | F91: =IF(F86>0,F85/F86,0) | G91: =IF(G86>0,G85/G86,0) | H91: =IF(H86>0,H85/H86,0) | I91: =IF(I86>0,I85/I86,0) | J91: =IF(J86>0,J85/J86,0) | K91: =IF(K86>0,K85/K86,0) | ... O91: =IF(O86>0,O85/O86,0)
A92: Porcentagem da renda
A93: Fixas | D93: =IF(D81>0,D82/D81,0) | E93: =IF(E81>0,E82/E81,0) | F93: =IF(F81>0,F82/F81,0) | G93: =IF(G81>0,G82/G81,0) | H93: =IF(H81>0,H82/H81,0) | I93: =IF(I81>0,I82/I81,0) | J93: =IF(J81>0,J82/J81,0) | K93: =IF(K81>0,K82/K81,0) | ... O93: =IF(O81>0,O82/O81,0)
A94: Variáveis | D94: =IF(D81>0,D83/D81,0) | E94: =IF(E81>0,E83/E81,0) | F94: =IF(F81>0,F83/F81,0) | G94: =IF(G81>0,G83/G81,0) | H94: =IF(H81>0,H83/H81,0) | I94: =IF(I81>0,I83/I81,0) | J94: =IF(J81>0,J83/J81,0) | K94: =IF(K81>0,K83/K81,0) | ... O94: =IF(O81>0,O83/O81,0)
A95: Extras | D95: =IF(D81>0,D84/D81,0) | E95: =IF(E81>0,E84/E81,0) | F95: =IF(F81>0,F84/F81,0) | G95: =IF(G81>0,G84/G81,0) | H95: =IF(H81>0,H84/H81,0) | I95: =IF(I81>0,I84/I81,0) | J95: =IF(J81>0,J84/J81,0) | K95: =IF(K81>0,K84/K81,0) | ... O95: =IF(O81>0,O84/O81,0)
A96: Adicionais | D96: =IF(D81>0,D85/D81,0) | E96: =IF(E81>0,E85/E81,0) | F96: =IF(F81>0,F85/F81,0) | G96: =IF(G81>0,G85/G81,0) | H96: =IF(H81>0,H85/H81,0) | I96: =IF(I81>0,I85/I81,0) | J96: =IF(J81>0,J85/J81,0) | K96: =IF(K81>0,K85/K81,0) | ... O96: =IF(O81>0,O85/O81,0)
A97: Saldo | D97: =D81-D86 | E97: =E81-E86 | F97: =F81-F86 | G97: =G81-G86 | H97: =H81-H86 | I97: =I81-I86 | J97: =J81-J86 | K97: =K81-K86 | ... O97: =O81-O86

Sheet Receitas
A1: Mês | C1: Janeiro | F1: Fevereiro | I1: Março | L1: Abril | O1: Maio | R1: Junho | U1: Julho | X1: Agosto | AA1: Setembro | AD1: Outubro | AG1: Novembro | AJ1: Dezembro
C2: Item | D2: Data | E2: Valor | F2: Item | G2: Data | H2: Valor | I2: Item | J2: Data | K2: Valor | L2: Item | M2: Data | N2: Valor | O2: Item | P2: Data | Q2: Valor | R2: Item | S2: Data | T2: Valor | U2: Item | V2: Data | W2: Valor | X2: Item | Y2: Data | Z2: Valor | AA2: Item | AB2: Data | AC2: Valor | AD2: Item | AE2: Data | AF2: Valor | AG2: Item | AH2: Data | AI2: Valor | AJ2: Item | AK2: Data | AL2: Valor
A3: Receita | B3: Salário | C3: Salário | D3: 46027 | E3: 5000 | F3: Salário | G3: 46058 | H3: 5000
C4: Total | D4: – | E4: =SUM(E3:E3) | F4: Total | G4: – | H4: =SUM(H3:H3) | I4: Total | J4: – | K4: =SUM(K3:K3) | L4: Total | M4: – | N4: =SUM(N3:N3) | O4: Total | P4: – | Q4: =SUM(Q3:Q3) | R4: Total | S4: – | T4: =SUM(T3:T3) | U4: Total | V4: – | W4: =SUM(W3:W3) | X4: Total | Y4: – | Z4: =SUM(Z3:Z3) | AA4: Total | AB4: – | AC4: =SUM(AC3:AC3) | AD4: Total | AE4: – | AF4: =SUM(AF3:AF3) | AG4: Total | AH4: – | AI4: =SUM(AI3:AI3) | AJ4: Total | AK4: – | AL4: =SUM(AL3:AL3)
B5: 13° | C5: 13° parcela | D5: 46042 | E5: 2500 | F5: 13° parcela | G5: 46073 | H5: 2500
C6: Total | D6: – | E6: =SUM(E5:E5) | F6: Total | G6: – | H6: =SUM(H5:H5) | I6: Total | J6: – | K6: =SUM(K5:K5) | L6: Total | M6: – | N6: =SUM(N5:N5) | O6: Total | P6: – | Q6: =SUM(Q5:Q5) | R6: Total | S6: – | T6: =SUM(T5:T5) | U6: Total | V6: – | W6: =SUM(W5:W5) | X6: Total | Y6: – | Z6: =SUM(Z5:Z5) | AA6: Total | AB6: – | AC6: =SUM(AC5:AC5) | AD6: Total | AE6: – | AF6: =SUM(AF5:AF5) | AG6: Total | AH6: – | AI6: =SUM(AI5:AI5) | AJ6: Total | AK6: – | AL6: =SUM(AL5:AL5)

Sheet Fixas
A1: Mês | C1: Janeiro | F1: Fevereiro | I1: Março | L1: Abril | O1: Maio | R1: Junho | U1: Julho | X1: Agosto | AA1: Setembro | AD1: Outubro | AG1: Novembro | AJ1: Dezembro
C2: Item | D2: Data | E2: Valor | F2: Item | G2: Data | H2: Valor | I2: Item | J2: Data | K2: Valor | L2: Item | M2: Data | N2: Valor | O2: Item | P2: Data | Q2: Valor | R2: Item | S2: Data | T2: Valor | U2: Item | V2: Data | W2: Valor | X2: Item | Y2: Data | Z2: Valor | AA2: Item | AB2: Data | AC2: Valor | AD2: Item | AE2: Data | AF2: Valor | AG2: Item | AH2: Data | AI2: Valor | AJ2: Item | AK2: Data | AL2: Valor
A3: Habitação | B3: Diarista | C3: Diarista | D3: 46025 | E3: 150 | F3: Diarista | G3: 46060 | H3: 150
C4: Diarista | D4: 46032 | E4: 160 | F4: Diarista | G4: 46067 | H4: 165
C5: Diarista | D5: 46039 | E5: 155.5 | F5: Diarista | G5: 46074 | H5: 158
C6: Total | D6: – | E6: =SUM(E3:E5) | F6: Total | G6: – | H6: =SUM(H3:H5) | I6: Total | J6: – | K6: =SUM(K3:K5) | L6: Total | M6: – | N6: =SUM(N3:N5) | O6: Total | P6: – | Q6: =SUM(Q3:Q5) | R6: Total | S6: – | T6: =SUM(T3:T5) | U6: Total | V6: – | W6: =SUM(W3:W5) | X6: Total | Y6: – | Z6: =SUM(Z3:Z5) | AA6: Total | AB6: – | AC6: =SUM(AC3:AC5) | AD6: Total | AE6: – | AF6: =SUM(AF3:AF5) | AG6: Total | AH6: – | AI6: =SUM(AI3:AI5) | AJ6: Total | AK6: – | AL6: =SUM(AL3:AL5)
B7: Aluguel | C7: Aluguel | D7: 46027 | E7: 1200 | F7: Aluguel | G7: 46058 | H7: 1200
C8: Condomínio | D8: 46027 | E8: 380.75
C9: Total | D9: – | E9: =SUM(E7:E8) | F9: Total | G9: – | H9: =SUM(H7:H8) | I9: Total | J9: – | K9: =SUM(K7:K8) | L9: Total | M9: – | N9: =SUM(N7:N8) | O9: Total | P9: – | Q9: =SUM(Q7:Q8) | R9: Total | S9: – | T9: =SUM(T7:T8) | U9: Total | V9: – | W9: =SUM(W7:W8) | X9: Total | Y9: – | Z9: =SUM(Z7:Z8) | AA9: Total | AB9: – | AC9: =SUM(AC7:AC8) | AD9: Total | AE9: – | AF9: =SUM(AF7:AF8) | AG9: Total | AH9: – | AI9: =SUM(AI7:AI8) | AJ9: Total | AK9: – | AL9: =SUM(AL7:AL8)
A13: Lazer | B13: Netflix | C13: Netflix | D13: 46024 | E13: 39.9 | F13: Netflix | G13: 46055 | H13: 39.9
C14: Total | D14: – | E14: =SUM(E13:E13) | F14: Total | G14: – | H14: =SUM(H13:H13) | I14: Total | J14: – | K14: =SUM(K13:K13) | L14: Total | M14: – | N14: =SUM(N13:N13) | O14: Total | P14: – | Q14: =SUM(Q13:Q13) | R14: Total | S14: – | T14: =SUM(T13:T13) | U14: Total | V14: – | W14: =SUM(W13:W13) | X14: Total | Y14: – | Z14: =SUM(Z13:Z13) | AA14: Total | AB14: – | AC14: =SUM(AC13:AC13) | AD14: Total | AE14: – | AF14: =SUM(AF13:AF13) | AG14: Total | AH14: – | AI14: =SUM(AI13:AI13) | AJ14: Total | AK14: – | AL14: =SUM(AL13:AL13)
B15: Spotify | C15: Spotify | D15: 46030 | E15: 19.9 | F15: Spotify | G15: 46061 | H15: 21.9
C16: Total | D16: – | E16: =SUM(E15:E15) | F16: Total | G16: – | H16: =SUM(H15:H15) | I16: Total | J16: – | K16: =SUM(K15:K15) | L16: Total | M16: – | N16: =SUM(N15:N15) | O16: Total | P16: – | Q16: =SUM(Q15:Q15) | R16: Total | S16: – | T16: =SUM(T15:T15) | U16: Total | V16: – | W16: =SUM(W15:W15) | X16: Total | Y16: – | Z16: =SUM(Z15:Z15) | AA16: Total | AB16: – | AC16: =SUM(AC15:AC15) | AD16: Total | AE16: – | AF16: =SUM(AF15:AF15) | AG16: Total | AH16: – | AI16: =SUM(AI15:AI15) | AJ16: Total | AK16: – | AL16: =SUM(AL15:AL15)

Sheet Variáveis
A1: Mês | C1: Janeiro | F1: Fevereiro | I1: Março | L1: Abril | O1: Maio | R1: Junho | U1: Julho | X1: Agosto | AA1: Setembro | AD1: Outubro | AG1: Novembro | AJ1: Dezembro
C2: Item | D2: Data | E2: Valor | F2: Item | G2: Data | H2: Valor | I2: Item | J2: Data | K2: Valor | L2: Item | M2: Data | N2: Valor | O2: Item | P2: Data | Q2: Valor | R2: Item | S2: Data | T2: Valor | U2: Item | V2: Data | W2: Valor | X2: Item | Y2: Data | Z2: Valor | AA2: Item | AB2: Data | AC2: Valor | AD2: Item | AE2: Data | AF2: Valor | AG2: Item | AH2: Data | AI2: Valor | AJ2: Item | AK2: Data | AL2: Valor
A3: Alimentação / Limpeza | B3: Supermercado | C3: Mercado | D3: 46028 | E3: 543.21 | F3: Mercado | G3: 46062 | H3: 612
C4: Total | D4: – | E4: =SUM(E3:E3) | F4: Total | G4: – | H4: =SUM(H3:H3) | I4: Total | J4: – | K4: =SUM(K3:K3) | L4: Total | M4: – | N4: =SUM(N3:N3) | O4: Total | P4: – | Q4: =SUM(Q3:Q3) | R4: Total | S4: – | T4: =SUM(T3:T3) | U4: Total | V4: – | W4: =SUM(W3:W3) | X4: Total | Y4: – | Z4: =SUM(Z3:Z3) | AA4: Total | AB4: – | AC4: =SUM(AC3:AC3) | AD4: Total | AE4: – | AF4: =SUM(AF3:AF3) | AG4: Total | AH4: – | AI4: =SUM(AI3:AI3) | AJ4: Total | AK4: – | AL4: =SUM(AL3:AL3)
B5: Padaria | C5: Padaria | D5: 46026 | E5: 45 | F5: Padaria | G5: 46065 | H5: 52.3
C6: Total | D6: – | E6: =SUM(E5:E5) | F6: Total | G6: – | H6: =SUM(H5:H5) | I6: Total | J6: – | K6: =SUM(K5:K5) | L6: Total | M6: – | N6: =SUM(N5:N5) | O6: Total | P6: – | Q6: =SUM(Q5:Q5) | R6: Total | S6: – | T6: =SUM(T5:T5) | U6: Total | V6: – | W6: =SUM(W5:W5) | X6: Total | Y6: – | Z6: =SUM(Z5:Z5) | AA6: Total | AB6: – | AC6: =SUM(AC5:AC5) | AD6: Total | AE6: – | AF6: =SUM(AF5:AF5) | AG6: Total | AH6: – | AI6: =SUM(AI5:AI5) | AJ6: Total | AK6: – | AL6: =SUM(AL5:AL5)
A10: Pets | B10: Orion - Consultas | C10: Consulta | D10: 46037 | E10: 200 | F10: Consulta | G10: 46071 | H10: 210
C11: Total | D11: – | E11: =SUM(E10:E10) | F11: Total | G11: – | H11: =SUM(H10:H10) | I11: Total | J11: – | K11: =SUM(K10:K10) | L11: Total | M11: – | N11: =SUM(N10:N10) | O11: Total | P11: – | Q11: =SUM(Q10:Q10) | R11: Total | S11: – | T11: =SUM(T10:T10) | U11: Total | V11: – | W11: =SUM(W10:W10) | X11: Total | Y11: – | Z11: =SUM(Z10:Z10) | AA11: Total | AB11: – | AC11: =SUM(AC10:AC10) | AD11: Total | AE11: – | AF11: =SUM(AF10:AF10) | AG11: Total | AH11: – | AI11: =SUM(AI10:AI10) | AJ11: Total | AK11: – | AL11: =SUM(AL10:AL10)
B12: Orion - Ração | C12: Ração | D12: 46023 | E12: 120 | F12: Ração | G12: 46056 | H12: 120
C13: Total | D13: – | E13: =SUM(E12:E12) | F13: Total | G13: – | H13: =SUM(H12:H12) | I13: Total | J13: – | K13: =SUM(K12:K12) | L13: Total | M13: – | N13: =SUM(N12:N12) | O13: Total | P13: – | Q13: =SUM(Q12:Q12) | R13: Total | S13: – | T13: =SUM(T12:T12) | U13: Total | V13: – | W13: =SUM(W12:W12) | X13: Total | Y13: – | Z13: =SUM(Z12:Z12) | AA13: Total | AB13: – | AC13: =SUM(AC12:AC12) | AD13: Total | AE13: – | AF13: =SUM(AF12:AF12) | AG13: Total | AH13: – | AI13: =SUM(AI12:AI12) | AJ13: Total | AK13: – | AL13: =SUM(AL12:AL12)
A17: Transporte | B17: Metrô | C17: Bilhete | D17: 46023 | E17: 100 | F17: Bilhete | G17: 46054 | H17: 100
C18: Total | D18: – | E18: =SUM(E17:E17) | F18: Total | G18: – | H18: =SUM(H17:H17) | I18: Total | J18: – | K18: =SUM(K17:K17) | L18: Total | M18: – | N18: =SUM(N17:N17) | O18: Total | P18: – | Q18: =SUM(Q17:Q17) | R18: Total | S18: – | T18: =SUM(T17:T17) | U18: Total | V18: – | W18: =SUM(W17:W17) | X18: Total | Y18: – | Z18: =SUM(Z17:Z17) | AA18: Total | AB18: – | AC18: =SUM(AC17:AC17) | AD18: Total | AE18: – | AF18: =SUM(AF17:AF17) | AG18: Total | AH18: – | AI18: =SUM(AI17:AI17) | AJ18: Total | AK18: – | AL18: =SUM(AL17:AL17)

Sheet Extras
A1: Mês | C1: Janeiro | F1: Fevereiro | I1: Março | L1: Abril | O1: Maio | R1: Junho | U1: Julho | X1: Agosto | AA1: Setembro | AD1: Outubro | AG1: Novembro | AJ1: Dezembro
C2: Item | D2: Data | E2: Valor | F2: Item | G2: Data | H2: Valor | I2: Item | J2: Data | K2: Valor | L2: Item | M2: Data | N2: Valor | O2: Item | P2: Data | Q2: Valor | R2: Item | S2: Data | T2: Valor | U2: Item | V2: Data | W2: Valor | X2: Item | Y2: Data | Z2: Valor | AA2: Item | AB2: Data | AC2: Valor | AD2: Item | AE2: Data | AF2: Valor | AG2: Item | AH2: Data | AI2: Valor | AJ2: Item | AK2: Data | AL2: Valor
A3: Saúde | B3: Médico | C3: Consulta | D3: 46032 | E3: 300 | F3: Consulta | G3: 46073 | H3: 320
C4: Total | D4: – | E4: =SUM(E3:E3) | F4: Total | G4: – | H4: =SUM(H3:H3) | I4: Total | J4: – | K4: =SUM(K3:K3) | L4: Total | M4: – | N4: =SUM(N3:N3) | O4: Total | P4: – | Q4: =SUM(Q3:Q3) | R4: Total | S4: – | T4: =SUM(T3:T3) | U4: Total | V4: – | W4: =SUM(W3:W3) | X4: Total | Y4: – | Z4: =SUM(Z3:Z3) | AA4: Total | AB4: – | AC4: =SUM(AC3:AC3) | AD4: Total | AE4: – | AF4: =SUM(AF3:AF3) | AG4: Total | AH4: – | AI4: =SUM(AI3:AI3) | AJ4: Total | AK4: – | AL4: =SUM(AL3:AL3)
B5: Dentista | C5: Limpeza | D5: 46033 | E5: 250 | F5: Limpeza | G5: 46064 | H5: 250
C6: Total | D6: – | E6: =SUM(E5:E5) | F6: Total | G6: – | H6: =SUM(H5:H5) | I6: Total | J6: – | K6: =SUM(K5:K5) | L6: Total | M6: – | N6: =SUM(N5:N5) | O6: Total | P6: – | Q6: =SUM(Q5:Q5) | R6: Total | S6: – | T6: =SUM(T5:T5) | U6: Total | V6: – | W6: =SUM(W5:W5) | X6: Total | Y6: – | Z6: =SUM(Z5:Z5) | AA6: Total | AB6: – | AC6: =SUM(AC5:AC5) | AD6: Total | AE6: – | AF6: =SUM(AF5:AF5) | AG6: Total | AH6: – | AI6: =SUM(AI5:AI5) | AJ6: Total | AK6: – | AL6: =SUM(AL5:AL5)
A10: Manutenção / prevenção | B10: Carro | C10: Revisão | D10: 46031 | E10: 480 | F10: Pneu | G10: 46062 | H10: 600
C11: Total | D11: – | E11: =SUM(E10:E10) | F11: Total | G11: – | H11: =SUM(H10:H10) | I11: Total | J11: – | K11: =SUM(K10:K10) | L11: Total | M11: – | N11: =SUM(N10:N10) | O11: Total | P11: – | Q11: =SUM(Q10:Q10) | R11: Total | S11: – | T11: =SUM(T10:T10) | U11: Total | V11: – | W11: =SUM(W10:W10) | X11: Total | Y11: – | Z11: =SUM(Z10:Z10) | AA11: Total | AB11: – | AC11: =SUM(AC10:AC10) | AD11: Total | AE11: – | AF11: =SUM(AF10:AF10) | AG11: Total | AH11: – | AI11: =SUM(AI10:AI10) | AJ11: Total | AK11: – | AL11: =SUM(AL10:AL10)
B12: Casa | C12: Pintura | D12: 46036 | E12: 350 | F12: Pintura | G12: 46067 | H12: 350
C13: Total | D13: – | E13: =SUM(E12:E12) | F13: Total | G13: – | H13: =SUM(H12:H12) | I13: Total | J13: – | K13: =SUM(K12:K12) | L13: Total | M13: – | N13: =SUM(N12:N12) | O13: Total | P13: – | Q13: =SUM(Q12:Q12) | R13: Total | S13: – | T13: =SUM(T12:T12) | U13: Total | V13: – | W13: =SUM(W12:W12) | X13: Total | Y13: – | Z13: =SUM(Z12:Z12) | AA13: Total | AB13: – | AC13: =SUM(AC12:AC12) | AD13: Total | AE13: – | AF13: =SUM(AF12:AF12) | AG13: Total | AH13: – | AI13: =SUM(AI12:AI12) | AJ13: Total | AK13: – | AL13: =SUM(AL12:AL12)

Sheet Adicionais
A1: Mês | C1: Janeiro | F1: Fevereiro | I1: Março | L1: Abril | O1: Maio | R1: Junho | U1: Julho | X1: Agosto | AA1: Setembro | AD1: Outubro | AG1: Novembro | AJ1: Dezembro
C2: Item | D2: Data | E2: Valor | F2: Item | G2: Data | H2: Valor | I2: Item | J2: Data | K2: Valor | L2: Item | M2: Data | N2: Valor | O2: Item | P2: Data | Q2: Valor | R2: Item | S2: Data | T2: Valor | U2: Item | V2: Data | W2: Valor | X2: Item | Y2: Data | Z2: Valor | AA2: Item | AB2: Data | AC2: Valor | AD2: Item | AE2: Data | AF2: Valor | AG2: Item | AH2: Data | AI2: Valor | AJ2: Item | AK2: Data | AL2: Valor
A3: Lazer | B3: Viagens | C3: Hotel | D3: 46025 | E3: 800 | F3: Passagem | G3: 46057 | H3: 950
C4: Total | D4: – | E4: =SUM(E3:E3) | F4: Total | G4: – | H4: =SUM(H3:H3) | I4: Total | J4: – | K4: =SUM(K3:K3) | L4: Total | M4: – | N4: =SUM(N3:N3) | O4: Total | P4: – | Q4: =SUM(Q3:Q3) | R4: Total | S4: – | T4: =SUM(T3:T3) | U4: Total | V4: – | W4: =SUM(W3:W3) | X4: Total | Y4: – | Z4: =SUM(Z3:Z3) | AA4: Total | AB4: – | AC4: =SUM(AC3:AC3) | AD4: Total | AE4: – | AF4: =SUM(AF3:AF3) | AG4: Total | AH4: – | AI4: =SUM(AI3:AI3) | AJ4: Total | AK4: – | AL4: =SUM(AL3:AL3)
B5: Jogos | C5: Steam | D5: 46029 | E5: 99.9 | F5: Steam | G5: 46060 | H5: 99.9
C6: Total | D6: – | E6: =SUM(E5:E5) | F6: Total | G6: – | H6: =SUM(H5:H5) | I6: Total | J6: – | K6: =SUM(K5:K5) | L6: Total | M6: – | N6: =SUM(N5:N5) | O6: Total | P6: – | Q6: =SUM(Q5:Q5) | R6: Total | S6: – | T6: =SUM(T5:T5) | U6: Total | V6: – | W6: =SUM(W5:W5) | X6: Total | Y6: – | Z6: =SUM(Z5:Z5) | AA6: Total | AB6: – | AC6: =SUM(AC5:AC5) | AD6: Total | AE6: – | AF6: =SUM(AF5:AF5) | AG6: Total | AH6: – | AI6: =SUM(AI5:AI5) | AJ6: Total | AK6: – | AL6: =SUM(AL5:AL5)
A10: Outros | B10: Presentes | C10: Presente | D10: 46027 | E10: 150 | F10: Presente | G10: 46058 | H10: 150
C11: Total | D11: – | E11: =SUM(E10:E10) | F11: Total | G11: – | H11: =SUM(H10:H10) | I11: Total | J11: – | K11: =SUM(K10:K10) | L11: Total | M11: – | N11: =SUM(N10:N10) | O11: Total | P11: – | Q11: =SUM(Q10:Q10) | R11: Total | S11: – | T11: =SUM(T10:T10) | U11: Total | V11: – | W11: =SUM(W10:W10) | X11: Total | Y11: – | Z11: =SUM(Z10:Z10) | AA11: Total | AB11: – | AC11: =SUM(AC10:AC10) | AD11: Total | AE11: – | AF11: =SUM(AF10:AF10) | AG11: Total | AH11: – | AI11: =SUM(AI10:AI10) | AJ11: Total | AK11: – | AL11: =SUM(AL10:AL10)
B12: Papelaria | C12: Caderno | D12: 46040 | E12: 45 | F12: Caneta | G12: 46071 | H12: 25
C13: Total | D13: – | E13: =SUM(E12:E12) | F13: Total | G13: – | H13: =SUM(H12:H12) | I13: Total | J13: – | K13: =SUM(K12:K12) | L13: Total | M13: – | N13: =SUM(N12:N12) | O13: Total | P13: – | Q13: =SUM(Q12:Q12) | R13: Total | S13: – | T13: =SUM(T12:T12) | U13: Total | V13: – | W13: =SUM(W12:W12) | X13: Total | Y13: – | Z13: =SUM(Z12:Z12) | AA13: Total | AB13: – | AC13: =SUM(AC12:AC12) | AD13: Total | AE13: – | AF13: =SUM(AF12:AF12) | AG13: Total | AH13: – | AI13: =SUM(AI12:AI12) | AJ13: Total | AK13: – | AL13: =SUM(AL12:AL12)
